<?xml version="1.0" encoding="UTF-8"?>
<!DOCTYPE hibernate-mapping PUBLIC "-//Hibernate/Hibernate Mapping DTD 3.0//EN" "http://hibernate.sourceforge.net/hibernate-mapping-3.0.dtd">
<!-- Generated 8 Aug, 2011 11:27:36 AM by Hibernate Tools 3.2.1.GA -->
<hibernate-mapping>
  <class catalog="libms" name="com.myapp.struts.hbm.AcqRecievingDetails" table="acq_recieving_details">
    <composite-id class="com.myapp.struts.hbm.AcqRecievingDetailsId" name="id">
      <key-property name="libraryId" type="string">
        <column length="20" name="library_id"/>
      </key-property>
      <key-property name="subLibraryId" type="string">
        <column length="20" name="sub_library_id"/>
      </key-property>
      <key-property name="recievingNo" type="string">
        <column length="20" name="recieving_no"/>
      </key-property>
      <key-property name="recievingItemId" type="int">
        <column name="recieving_item_id"/>
      </key-property>
    </composite-id>
    <property name="titleId" type="java.lang.Integer">
      <column name="title_id"/>
    </property>
    <property name="unitPrice" type="string">
      <column length="10" name="unit_price"/>
    </property>
    <property name="recievedCopies" type="java.lang.Integer">
      <column name="recieved_copies"/>
    </property>
    <property name="pendingCopies" type="java.lang.Integer">
      <column name="pending_copies"/>
    </property>
    <property name="approvalType" type="string">
      <column length="20" name="approval_type"/>
    </property>
    <property name="controlNo" type="java.lang.Integer">
      <column name="control_no"/>
    </property>
    <property name="vendorId" type="string">
      <column length="20" name="vendor_id"/>
    </property>
    <property name="status" type="string">
      <column length="10" name="status"/>
    </property>
    <property name="time" type="timestamp">
      <column name="time"/>
    </property>
  </class>
</hibernate-mapping>
